[
  {
    "tag": "Complete Guide",
    "title": "Hair Transplant in Istanbul: Complete Guide for International Patients",
    "desc": "Everything you need to know before booking — costs, clinic standards, techniques, and what to expect.",
    "url": "/blog",
    "image": ""
  },
  {
    "tag": "Recovery",
    "title": "Month by Month: What to Expect After Your Hair Transplant",
    "desc": "A realistic timeline covering shock loss, new growth, and when you'll see final results.",
    "url": "/blog",
    "image": ""
  },
  {
    "tag": "Planning",
    "title": "FUE vs DHI: Which Technique Is Right for Your Hair Loss?",
    "desc": "The key differences explained — and how to know which approach suits your specific pattern.",
    "url": "/blog",
    "image": ""
  }
]
